edagames_grpc/__init__.py
edagames_grpc/client.py
edagames_grpc/eda_games_pb2.py
edagames_grpc/eda_games_pb2_grpc.py
edagames_grpc/game_start.py
edagames_grpc/game_state.py
edagames_grpc/server.py
edagames_grpc/utils.py
edagames_grpc-1.1.0.dist-info/LICENSE
edagames_grpc-1.1.0.dist-info/METADATA
edagames_grpc-1.1.0.dist-info/WHEEL
edagames_grpc-1.1.0.dist-info/top_level.txt
edagames_grpc-1.1.0.dist-info/RECORD
