Metadata-Version: 2.1
Name: edagames-grpc
Version: 1.1.0
Summary: Interface for gRPC communication
Home-page: https://github.com/evbeda/edagames-grpc
Author: Platform Team - EDA 5
Author-email: ecrespillo@eventbrite.com
License: UNKNOWN
Platform: UNKNOWN
Classifier: Programming Language :: Python :: 3
Classifier: License :: OSI Approved :: Apache Software License
Classifier: Operating System :: OS Independent
Classifier: Environment :: Console
Classifier: Intended Audience :: Developers
Requires-Python: >=3.6
Requires-Dist: grpcio (==1.37.0)
Requires-Dist: protobuf (==3.15.8)
